README.md
setup.cfg
setup.py
xeHentai/Untitled-1.py
xeHentai/__init__.py
xeHentai/cli.py
xeHentai/config.py
xeHentai/const.py
xeHentai/core.py
xeHentai/filters.py
xeHentai/proxy.py
xeHentai/rpc.py
xeHentai/task.py
xeHentai/worker.py
xeHentai.egg-info/PKG-INFO
xeHentai.egg-info/SOURCES.txt
xeHentai.egg-info/dependency_links.txt
xeHentai.egg-info/entry_points.txt
xeHentai.egg-info/not-zip-safe
xeHentai.egg-info/requires.txt
xeHentai.egg-info/top_level.txt
xeHentai/i18n/__init__.py
xeHentai/i18n/en_us.py
xeHentai/i18n/zh_hans.py
xeHentai/i18n/zh_hant.py
xeHentai/util/__init__.py
xeHentai/util/logger.py